Workbook

Sheet Product_Master
A1: Product_ID | B1: Product_Name | C1: Category | D1: Brand | E1: Unit_Price | F1: Stock
A2: P101 | B2: Laptop 14" Pro | C2: Electronics | D2: Dell | E2: 58000 | F2: 35
A3: P102 | B3: Laptop 15" Max | C3: Electronics | D3: HP | E3: 62000 | F3: 25 | I3: Normalizations | J3: Divions of Data into multiple groups is called normalization
A4: P103 | B4: Mouse Wireless | C4: Accessories | D4: Logitech | E4: 1200 | F4: 120 | I4: Primary Key | J4: Aaddhaar NO
A5: P104 | B5: Keyboard Mech. | C5: Accessories | D5: Redragon | E5: 2500 | F5: 90 | I5: Foreign Key
A6: P105 | B6: Smartwatch FitX | C6: Wearables | D6: Samsung | E6: 14500 | F6: 60
A7: P106 | B7: Smartphone X10 | C7: Mobile Phones | D7: Redmi | E7: 19999 | F7: 75
A8: P107 | B8: Tablet TabPro | C8: Electronics | D8: Lenovo | E8: 27500 | F8: 40
A9: P108 | B9: Earbuds Air 3 | C9: Audio | D9: Boat | E9: 2499 | F9: 150
A10: P109 | B10: Power Bank 20k | C10: Accessories | D10: MI | E10: 1899 | F10: 85
A11: P110 | B11: Bluetooth Speaker | C11: Audio | D11: JBL | E11: 3299 | F11: 45
I12: Personal Data | J12: Educational | K12: Police Verfication | L12: Experience
H13: Jayant | I13: 5 | J13: 4 | K13: 3 | L13: 6
H14: Cause | I14: Slow | J14: time | K14: Error | L14: Fail
B16: P106 | C16: =_xlfn.XLOOKUP(B16,A2:A11,E2:E11) -> 19999
C18: LookUp Value | D18: Look up array | E18: Return Array

Sheet Region_Master
A1: State | B1: Region
A2: Maharashtra | B2: West
A3: Gujarat | B3: West
A4: Delhi | B4: North
A5: Rajasthan | B5: North
A6: Kerala | B6: South
A7: Uttar Pradesh | B7: North
A8: Goa | B8: West
A9: Madhya Pradesh | B9: Central

Sheet Customer_Master
A1: Cust_ID | B1: Customer_Name | C1: City | D1: State | E1: Age | F1: Gender
A2: C001 | B2: Rajesh Sharma | C2: Mumbai | D2: Maharashtra | E2: 34 | F2: M
A3: C002 | B3: Anita Verma | C3: Pune | D3: Maharashtra | E3: 29 | F3: F
A4: C003 | B4: Sanjay Patel | C4: Ahmedabad | D4: Gujarat | E4: 41 | F4: M
A5: C004 | B5: Neha Gupta | C5: Delhi | D5: Delhi | E5: 27 | F5: F
A6: C005 | B6: Mohit Jain | C6: Jaipur | D6: Rajasthan | E6: 36 | F6: M
A7: C006 | B7: Priya Nair | C7: Kochi | D7: Kerala | E7: 31 | F7: F
A8: C007 | B8: Karan Singh | C8: Lucknow | D8: Uttar Pradesh | E8: 39 | F8: M
A9: C008 | B9: Riya D’Souza | C9: Goa | D9: Goa | E9: 26 | F9: F
A10: C009 | B10: Suresh Yadav | C10: Indore | D10: Madhya Pradesh | E10: 45 | F10: M
A11: C010 | B11: Pooja Deshmukh | C11: Nagpur | D11: Maharashtra | E11: 33 | F11: F

Sheet Sales_Data
A1: Invoice_ID | B1: Cust_ID | C1: Product_ID | D1: Quantity | E1: Invoice_Date | F1: product name | G1: Category
A2: INV001 | B2: C001 | C2: P103 | D2: 2 | E2: 2024-07-11 | F2: =_xlfn.XLOOKUP(C2,Product_Master!$A$2:$A$11,Product_Master!$B$2:$B$11,"Invalid Product") -> Mouse Wireless | G2: =_xlfn.XLOOKUP(C2,Product_Master!$A$2:$A$11,Product_Master!$C$2:$C$11) -> Accessories
A3: INV002 | B3: C004 | C3: P106 | D3: 1 | E3: 2024-07-12 | F3: =_xlfn.XLOOKUP(C3,Product_Master!$A$2:$A$11,Product_Master!$B$2:$B$11,"Invalid Product") -> Smartphone X10 | G3: =_xlfn.XLOOKUP(C3,Product_Master!$A$2:$A$11,Product_Master!$C$2:$C$11) -> Mobile Phones
A4: INV003 | B4: C009 | C4: P102 | D4: 1 | E4: 2024-07-15 | F4: =_xlfn.XLOOKUP(C4,Product_Master!$A$2:$A$11,Product_Master!$B$2:$B$11,"Invalid Product") -> Laptop 15" Max | G4: =_xlfn.XLOOKUP(C4,Product_Master!$A$2:$A$11,Product_Master!$C$2:$C$11) -> Electronics
A5: INV004 | B5: C003 | C5: P109 | D5: 3 | E5: 2024-07-18 | F5: =_xlfn.XLOOKUP(C5,Product_Master!$A$2:$A$11,Product_Master!$B$2:$B$11,"Invalid Product") -> Power Bank 20k | G5: =_xlfn.XLOOKUP(C5,Product_Master!$A$2:$A$11,Product_Master!$C$2:$C$11) -> Accessories
A6: INV005 | B6: C005 | C6: P108 | D6: 2 | E6: 2024-07-19 | F6: =_xlfn.XLOOKUP(C6,Product_Master!$A$2:$A$11,Product_Master!$B$2:$B$11,"Invalid Product") -> Earbuds Air 3 | G6: =_xlfn.XLOOKUP(C6,Product_Master!$A$2:$A$11,Product_Master!$C$2:$C$11) -> Audio
A7: INV006 | B7: C007 | C7: P110 | D7: 1 | E7: 2024-07-22 | F7: =_xlfn.XLOOKUP(C7,Product_Master!$A$2:$A$11,Product_Master!$B$2:$B$11,"Invalid Product") -> Bluetooth Speaker | G7: =_xlfn.XLOOKUP(C7,Product_Master!$A$2:$A$11,Product_Master!$C$2:$C$11) -> Audio
A8: INV007 | B8: C002 | C8: P101 | D8: 1 | E8: 2024-07-23 | F8: =_xlfn.XLOOKUP(C8,Product_Master!$A$2:$A$11,Product_Master!$B$2:$B$11,"Invalid Product") -> Laptop 14" Pro | G8: =_xlfn.XLOOKUP(C8,Product_Master!$A$2:$A$11,Product_Master!$C$2:$C$11) -> Electronics
A9: INV008 | B9: C010 | C9: P105 | D9: 1 | E9: 2024-07-25 | F9: =_xlfn.XLOOKUP(C9,Product_Master!$A$2:$A$11,Product_Master!$B$2:$B$11,"Invalid Product") -> Smartwatch FitX | G9: =_xlfn.XLOOKUP(C9,Product_Master!$A$2:$A$11,Product_Master!$C$2:$C$11) -> Wearables
A10: INV009 | B10: C006 | C10: P104 | D10: 2 | E10: 2024-07-26 | F10: =_xlfn.XLOOKUP(C10,Product_Master!$A$2:$A$11,Product_Master!$B$2:$B$11,"Invalid Product") -> Keyboard Mech. | G10: =_xlfn.XLOOKUP(C10,Product_Master!$A$2:$A$11,Product_Master!$C$2:$C$11) -> Accessories
A11: INV010 | B11: C008 | C11: P107 | D11: 1 | E11: 2024-07-28 | F11: =_xlfn.XLOOKUP(C11,Product_Master!$A$2:$A$11,Product_Master!$B$2:$B$11,"Invalid Product") -> Tablet TabPro | G11: =_xlfn.XLOOKUP(C11,Product_Master!$A$2:$A$11,Product_Master!$C$2:$C$11) -> Electronics
H14: Retrieve the Category for each Product_ID in Sales_Data.

Sheet Discount_Master
A1: Category | B1: Discount_Percent
A2: Electronics | B2: 0.1
A3: Accessories | B3: 5%
A4: Wearables | B4: 8%
A5: Mobile Phones | B5: 7%
A6: Audio | B6: 6%

Sheet Questions
A1: 🧠 XLOOKUP Practice Questions (20 Total)
A2: No | B2: Question
A3: 1 | B3: Find the Product Name for Product_ID = "P104".
A4: 2 | B4: Find the Brand Name for Product_ID = "P108".
A5: 3 | B5: Get the Customer Name for Cust_ID = "C007".
A6: 4 | B6: Retrieve the Category for each Product_ID in Sales_Data.
A7: 5 | B7: Find the Unit Price for each Product_ID in Sales_Data.
A8: 6 | B8: Add a column in Sales_Data to show Product_Name.
A9: 7 | B9: Add Customer_Name and City columns in Sales_Data using Cust_ID.
A10: 8 | B10: Get the State for each customer in Sales_Data.
A11: 9 | B11: Find the Region of each customer based on their State.
A12: 10 | B12: Retrieve the Discount % for each sale based on its Category.
A13: 11 | B13: Calculate Total Amount = Quantity × Unit Price for each sale.
A14: 12 | B14: Calculate Discount Value = Total × Discount % for each sale.
... A22: 20 | B22: Display Customer_Name, Product_Name, Region, and Net Amount all in one table.
